README.md
setup.py
MagicHome/MagicHome.py
MagicHome/__init__.py
MagicHome_python.egg-info/PKG-INFO
MagicHome_python.egg-info/SOURCES.txt
MagicHome_python.egg-info/dependency_links.txt
MagicHome_python.egg-info/top_level.txt