Metadata-Version: 2.1
Name: MagicHome-python
Version: 1.0.1
Summary: A Python library for MagicHome Wifi RGB controller
Home-page: UNKNOWN
Author: Marcel Bohland
Author-email: <opensearchapp@gmail.com>
License: UNKNOWN
Keywords: python,MagicHome,RGB,RGB controller,Wifi,sockets
Platform: UNKNOWN
Classifier: Development Status :: 1 - Planning
Classifier: Intended Audience :: Developers
Classifier: Programming Language :: Python :: 3
Classifier: Operating System :: Unix
Classifier: Operating System :: MacOS :: MacOS X
Classifier: Operating System :: Microsoft :: Windows
